csvmove/__init__.py
csvmove/main.py
csvmove-0.2.3.dist-info/entry_points.txt
csvmove-0.2.3.dist-info/LICENSE
csvmove-0.2.3.dist-info/METADATA
csvmove-0.2.3.dist-info/WHEEL
csvmove-0.2.3.dist-info/RECORD
